Metadata-Version: 2.1
Name: imstegapy
Version: 0.1.0
Summary: A small image steganography tool.
Home-page: https://github.com/Jedddy/imsteg
Author: Jedddy
License: MIT
License-File: LICENSE
